[
 {
  "table":"EDE2T",
  "index":
  [
   {
    "columns":
    [
     {
      "key":"MANDT",
      "value":"100"
     },
     {
      "key":"EVCODE",
      "value":"ZGITMATM"
     },
     {
      "key":"LANGUA",
      "value":"D"
     }
    ],
    "hash":"AvSL71Eyn4WvaTpu9QrUFDP5FsI="
   },
   {
    "columns":
    [
     {
      "key":"MANDT",
      "value":"100"
     },
     {
      "key":"EVCODE",
      "value":"ZGITMATM"
     },
     {
      "key":"LANGUA",
      "value":"E"
     }
    ],
    "hash":"RtSlyMS2CdVzUX9tT+8qyHGOwDc="
   },
   {
    "columns":
    [
     {
      "key":"MANDT",
      "value":"100"
     },
     {
      "key":"EVCODE",
      "value":"ZGITMATM"
     },
     {
      "key":"LANGUA",
      "value":"F"
     }
    ],
    "hash":"uYfvqZlsBY0jMVWqlnh1MEqVcdE="
   },
   {
    "columns":
    [
     {
      "key":"MANDT",
      "value":"100"
     },
     {
      "key":"EVCODE",
      "value":"ZGITMATM"
     },
     {
      "key":"LANGUA",
      "value":"N"
     }
    ],
    "hash":"uPNDIX8gxlTe57csIztwGRsF5zA="
   },
   {
    "columns":
    [
     {
      "key":"MANDT",
      "value":"100"
     },
     {
      "key":"EVCODE",
      "value":"ZGITMATM"
     },
     {
      "key":"LANGUA",
      "value":"P"
     }
    ],
    "hash":"IXK6159nTiUjSBkVqRFNuOshiVM="
   }
  ]
 },
 {
  "table":"TEDE2",
  "index":
  [
   {
    "columns":
    [
     {
      "key":"MANDT",
      "value":"100"
     },
     {
      "key":"EVCODE",
      "value":"ZGITMATM"
     }
    ],
    "hash":"Es4xzgmznYap1SW+QgLuO8/uzvU="
   }
  ]
 }
]