[
 {
  "table":"OBJH",
  "data":
  [
   {
    "OBJECTNAME":"SHI3",
    "OBJECTTYPE":"L",
    "CLIDEP":"",
    "LANGDEP":"X",
    "ALEDEP":"",
    "OBJCATEG":"SYST",
    "TRCOMPLETE":"",
    "TRDISJUNCT":"",
    "PHASELEVEL":0,
    "LOCKMETH":"",
    "TADIRCMETH":"",
    "CHECKID":"L",
    "OBJNAMELEN":32,
    "PROTECT":"",
    "OBJTRANSP":"2",
    "LUSER":"",
    "LDATE":"0000-00-00",
    "OBJNAMECLS":"",
    "CURSETTING":"",
    "OBJHASADDR":"",
    "IMPORTABLE":"",
    "OBJCHARSET":"",
    "MCCATEGORY":"",
    "MCDOCUID":"",
    "ABAP_LANGUAGE_VERSION":""
   }
  ]
 },
 {
  "table":"OBJM",
  "data":
  [
   {
    "OBJECTNAME":"SHI3",
    "OBJECTTYPE":"L",
    "METHOD":"AFTER_IMP",
    "METHODNAME":"STREE_AFTER_IMPORT",
    "UPGRADE":"X",
    "MULTI_OBJ":"X",
    "LANG_OBJ":"",
    "SHADOW_SYS":""
   },
   {
    "OBJECTNAME":"SHI3",
    "OBJECTTYPE":"L",
    "METHOD":"BEFORE_EXP",
    "METHODNAME":"STREE_BEFORE_EXPORT",
    "UPGRADE":"",
    "MULTI_OBJ":"X",
    "LANG_OBJ":"",
    "SHADOW_SYS":""
   }
  ]
 },
 {
  "table":"OBJS",
  "data":
  [
   {
    "OBJECTNAME":"SHI3",
    "OBJECTTYPE":"L",
    "TABNAME":"TCTM_LOOB",
    "COVER":"",
    "CANDIDATE":"",
    "DDIC":"X",
    "PRIM_TABLE":"",
    "VIEWGRANT":"",
    "TAB_FILLED":""
   },
   {
    "OBJECTNAME":"SHI3",
    "OBJECTTYPE":"L",
    "TABNAME":"TCTM_LPVAL",
    "COVER":"",
    "CANDIDATE":"",
    "DDIC":"X",
    "PRIM_TABLE":"",
    "VIEWGRANT":"",
    "TAB_FILLED":""
   },
   {
    "OBJECTNAME":"SHI3",
    "OBJECTTYPE":"L",
    "TABNAME":"TCTM_PHOB",
    "COVER":"",
    "CANDIDATE":"",
    "DDIC":"X",
    "PRIM_TABLE":"",
    "VIEWGRANT":"",
    "TAB_FILLED":""
   },
   {
    "OBJECTNAME":"SHI3",
    "OBJECTTYPE":"L",
    "TABNAME":"TCTM_PPV",
    "COVER":"",
    "CANDIDATE":"",
    "DDIC":"X",
    "PRIM_TABLE":"",
    "VIEWGRANT":"",
    "TAB_FILLED":""
   },
   {
    "OBJECTNAME":"SHI3",
    "OBJECTTYPE":"L",
    "TABNAME":"TTREE",
    "COVER":"",
    "CANDIDATE":"",
    "DDIC":"X",
    "PRIM_TABLE":"X",
    "VIEWGRANT":"",
    "TAB_FILLED":""
   },
   {
    "OBJECTNAME":"SHI3",
    "OBJECTTYPE":"L",
    "TABNAME":"TTREED",
    "COVER":"",
    "CANDIDATE":"",
    "DDIC":"X",
    "PRIM_TABLE":"",
    "VIEWGRANT":"",
    "TAB_FILLED":""
   },
   {
    "OBJECTNAME":"SHI3",
    "OBJECTTYPE":"L",
    "TABNAME":"TTREEI",
    "COVER":"",
    "CANDIDATE":"",
    "DDIC":"X",
    "PRIM_TABLE":"",
    "VIEWGRANT":"",
    "TAB_FILLED":""
   },
   {
    "OBJECTNAME":"SHI3",
    "OBJECTTYPE":"L",
    "TABNAME":"TTREEN",
    "COVER":"",
    "CANDIDATE":"",
    "DDIC":"X",
    "PRIM_TABLE":"",
    "VIEWGRANT":"",
    "TAB_FILLED":""
   },
   {
    "OBJECTNAME":"SHI3",
    "OBJECTTYPE":"L",
    "TABNAME":"TTREEP",
    "COVER":"",
    "CANDIDATE":"",
    "DDIC":"X",
    "PRIM_TABLE":"",
    "VIEWGRANT":"",
    "TAB_FILLED":""
   },
   {
    "OBJECTNAME":"SHI3",
    "OBJECTTYPE":"L",
    "TABNAME":"TTREET",
    "COVER":"",
    "CANDIDATE":"",
    "DDIC":"X",
    "PRIM_TABLE":"",
    "VIEWGRANT":"",
    "TAB_FILLED":""
   },
   {
    "OBJECTNAME":"SHI3",
    "OBJECTTYPE":"L",
    "TABNAME":"TTREE_APPL",
    "COVER":"",
    "CANDIDATE":"",
    "DDIC":"X",
    "PRIM_TABLE":"",
    "VIEWGRANT":"",
    "TAB_FILLED":""
   },
   {
    "OBJECTNAME":"SHI3",
    "OBJECTTYPE":"L",
    "TABNAME":"TTREE_FLNK",
    "COVER":"",
    "CANDIDATE":"",
    "DDIC":"X",
    "PRIM_TABLE":"",
    "VIEWGRANT":"",
    "TAB_FILLED":""
   }
  ]
 },
 {
  "table":"OBJSL",
  "data":
  [
   {
    "OBJECTNAME":"SHI3",
    "OBJECTTYPE":"L",
    "TRWCOUNT":1,
    "TPGMID":"R3TR",
    "TOBJECT":"TABU",
    "TOBJ_NAME":"TTREE",
    "TOBJKEY":"/&",
    "MASKNLEN":5,
    "MASKKLEN":1,
    "PRIM_TABLE":"X"
   },
   {
    "OBJECTNAME":"SHI3",
    "OBJECTTYPE":"L",
    "TRWCOUNT":2,
    "TPGMID":"R3TR",
    "TOBJECT":"TABU",
    "TOBJ_NAME":"TTREEI",
    "TOBJKEY":"/&/*",
    "MASKNLEN":6,
    "MASKKLEN":2,
    "PRIM_TABLE":""
   },
   {
    "OBJECTNAME":"SHI3",
    "OBJECTTYPE":"L",
    "TRWCOUNT":3,
    "TPGMID":"R3TR",
    "TOBJECT":"TABU",
    "TOBJ_NAME":"TTREEN",
    "TOBJKEY":"/&/*",
    "MASKNLEN":6,
    "MASKKLEN":2,
    "PRIM_TABLE":""
   },
   {
    "OBJECTNAME":"SHI3",
    "OBJECTTYPE":"L",
    "TRWCOUNT":5,
    "TPGMID":"R3TR",
    "TOBJECT":"TABU",
    "TOBJ_NAME":"TTREET",
    "TOBJKEY":"/L/&",
    "MASKNLEN":6,
    "MASKKLEN":2,
    "PRIM_TABLE":""
   },
   {
    "OBJECTNAME":"SHI3",
    "OBJECTTYPE":"L",
    "TRWCOUNT":6,
    "TPGMID":"R3TR",
    "TOBJECT":"TABU",
    "TOBJ_NAME":"TTREEP",
    "TOBJKEY":"/&/*",
    "MASKNLEN":6,
    "MASKKLEN":2,
    "PRIM_TABLE":""
   },
   {
    "OBJECTNAME":"SHI3",
    "OBJECTTYPE":"L",
    "TRWCOUNT":7,
    "TPGMID":"R3TR",
    "TOBJECT":"TABU",
    "TOBJ_NAME":"TTREE_APPL",
    "TOBJKEY":"/&/*",
    "MASKNLEN":10,
    "MASKKLEN":2,
    "PRIM_TABLE":""
   },
   {
    "OBJECTNAME":"SHI3",
    "OBJECTTYPE":"L",
    "TRWCOUNT":8,
    "TPGMID":"R3TR",
    "TOBJECT":"TABU",
    "TOBJ_NAME":"TTREE_FLNK",
    "TOBJKEY":"/&/*",
    "MASKNLEN":10,
    "MASKKLEN":2,
    "PRIM_TABLE":""
   },
   {
    "OBJECTNAME":"SHI3",
    "OBJECTTYPE":"L",
    "TRWCOUNT":9,
    "TPGMID":"R3TR",
    "TOBJECT":"TABU",
    "TOBJ_NAME":"TTREED",
    "TOBJKEY":"/&/*",
    "MASKNLEN":6,
    "MASKKLEN":2,
    "PRIM_TABLE":""
   },
   {
    "OBJECTNAME":"SHI3",
    "OBJECTTYPE":"L",
    "TRWCOUNT":10,
    "TPGMID":"R3TR",
    "TOBJECT":"TABU",
    "TOBJ_NAME":"TCTM_PHOB",
    "TOBJKEY":"SHI3/&/*",
    "MASKNLEN":9,
    "MASKKLEN":6,
    "PRIM_TABLE":""
   },
   {
    "OBJECTNAME":"SHI3",
    "OBJECTTYPE":"L",
    "TRWCOUNT":13,
    "TPGMID":"R3TR",
    "TOBJECT":"TABU",
    "TOBJ_NAME":"TCTM_LOOB",
    "TOBJKEY":"SHI3/&/*",
    "MASKNLEN":9,
    "MASKKLEN":6,
    "PRIM_TABLE":""
   },
   {
    "OBJECTNAME":"SHI3",
    "OBJECTTYPE":"L",
    "TRWCOUNT":15,
    "TPGMID":"R3TR",
    "TOBJECT":"TABU",
    "TOBJ_NAME":"TCTM_LPVAL",
    "TOBJKEY":"SHI3/&/*",
    "MASKNLEN":10,
    "MASKKLEN":6,
    "PRIM_TABLE":""
   },
   {
    "OBJECTNAME":"SHI3",
    "OBJECTTYPE":"L",
    "TRWCOUNT":16,
    "TPGMID":"R3TR",
    "TOBJECT":"TABU",
    "TOBJ_NAME":"TCTM_PPV",
    "TOBJKEY":"SHI3/&/*",
    "MASKNLEN":8,
    "MASKKLEN":6,
    "PRIM_TABLE":""
   }
  ]
 },
 {
  "table":"OBJT",
  "data":
  [
   {
    "LANGUAGE":"D",
    "OBJECTNAME":"SHI3",
    "OBJECTTYPE":"L",
    "DDTEXT":"Allgemeine Strukturablage: Definition einer Struktur"
   },
   {
    "LANGUAGE":"E",
    "OBJECTNAME":"SHI3",
    "OBJECTTYPE":"L",
    "DDTEXT":"General structure storage: Definition of a structure"
   },
   {
    "LANGUAGE":"F",
    "OBJECTNAME":"SHI3",
    "OBJECTTYPE":"L",
    "DDTEXT":"Arch. structures général : définition d´une structure"
   },
   {
    "LANGUAGE":"N",
    "OBJECTNAME":"SHI3",
    "OBJECTTYPE":"L",
    "DDTEXT":"Algemene structuuropslag: definitie van een structuur"
   },
   {
    "LANGUAGE":"P",
    "OBJECTNAME":"SHI3",
    "OBJECTTYPE":"L",
    "DDTEXT":"Arquivo de estrutura geral: definição de uma estrutura"
   }
  ]
 }
]